{"is_source_file": true, "format": "Kotlin DSL (Gradle Kotlin Script)", "description": "This file configures plugin management, repositories, and module inclusion for an Android project using Kotlin DSL in Gradle.", "external_files": ["local.properties"], "external_methods": ["file()", "properties.load()", "properties.getProperty()", "require()"], "published": [], "classes": [], "methods": [{"name": "run", "description": "Executes a block to retrieve the flutterSdkPath based on local properties."}], "calls": ["file().inputStream()", "properties.load()", "properties.getProperty()", "require()"], "search-terms": ["gradle plugin management", "flutter SDK path configuration", "plugin definitions", "include build", "repositories setup"], "state": 2, "file_id": 13, "knowledge_revision": 31, "git_revision": "956ce37bc83d1b4c3f245607db709ca8fa3057fc", "hash": "683f9ca2f32a701ed1517715bf394e23", "format-version": 4, "code-base-name": "android_tv_frontend", "filename": "android_tv_frontend/android/settings.gradle.kts", "revision_history": [{"31": "956ce37bc83d1b4c3f245607db709ca8fa3057fc"}]}